mbq/__init__.py
mbq/metrics/__init__.py
mbq/metrics/utils.py
mbq.metrics-0.0.2.dist-info/DESCRIPTION.rst
mbq.metrics-0.0.2.dist-info/METADATA
mbq.metrics-0.0.2.dist-info/RECORD
mbq.metrics-0.0.2.dist-info/WHEEL
mbq.metrics-0.0.2.dist-info/metadata.json
mbq.metrics-0.0.2.dist-info/top_level.txt
mbq.metrics-0.0.2.dist-info/zip-safe
tests/__init__.py
tests/compat.py
tests/test_collector.py
tests/test_utils.py
